momlevel/__init__.py
momlevel/derived.py
momlevel/dynamic.py
momlevel/reference.py
momlevel/steric.py
momlevel/tidegauge.py
momlevel/trend.py
momlevel/util.py
momlevel/eos/__init__.py
momlevel/eos/linear.py
momlevel/eos/wright.py
momlevel/resources/CM4_historical.nc
momlevel/resources/NWA12_grid_dataframe.csv
momlevel/resources/NWA12_sample_grid_data.nc
momlevel/resources/geolocate_points_reference.csv
momlevel/resources/global_tide_gauges.csv
momlevel/resources/us_tide_gauges.csv
momlevel/spice/__init__.py
momlevel/spice/flament.py
momlevel/test_data/__init__.py
momlevel/test_data/time.py
momlevel/test_data/tripolar/__init__.py
momlevel/test_data/tripolar/horizontal.py
momlevel/test_data/tripolar/vertical.py
momlevel-1.0.4.dist-info/licenses/LICENSE.txt
momlevel-1.0.4.dist-info/METADATA
momlevel-1.0.4.dist-info/WHEEL
momlevel-1.0.4.dist-info/top_level.txt
momlevel-1.0.4.dist-info/RECORD
