Metadata-Version: 2.4
Name: momlevel
Version: 1.0.4
Summary: Tools to diagnose sea level in the MOM Ocean Model
Author-email: John Krasting <john.krasting@noaa.gov>
License: Software code created by U.S. Government employees is not subject to copyright in the United States (17 U.S.C. §105).
Project-URL: homepage, https://github.com/jkrasting/momlevel
Project-URL: documentation, https://momlevel.readthedocs.io
Project-URL: repository, https://github.com/jkrasting/momlevel
Keywords: oceanography,sealevel,sea-level,slr,mom,mom6,model,ocean
Classifier: Development Status :: 3 - Alpha
Classifier: Intended Audience :: Science/Research
Classifier: Topic :: Scientific/Engineering
Classifier: License :: Public Domain
Classifier: Programming Language :: Python :: 3.8
Classifier: Programming Language :: Python :: 3.9
Requires-Python: >=3.8
License-File: LICENSE.txt
Requires-Dist: importlib_metadata<5.0.0
Requires-Dist: nc-time-axis
Requires-Dist: netcdf4
Requires-Dist: numpy>=1.21.0
Requires-Dist: scikit-learn>=1.0.1
Requires-Dist: xarray>=0.20.0
Requires-Dist: xgcm
Provides-Extra: test
Requires-Dist: pytest; extra == "test"
Dynamic: license-file
